pytest_nodev/__init__.py
pytest_nodev/blacklists.py
pytest_nodev/collect.py
pytest_nodev/plugin.py
pytest_nodev/utils.py
pytest_nodev-1.0.1.dist-info/DESCRIPTION.rst
pytest_nodev-1.0.1.dist-info/METADATA
pytest_nodev-1.0.1.dist-info/RECORD
pytest_nodev-1.0.1.dist-info/WHEEL
pytest_nodev-1.0.1.dist-info/entry_points.txt
pytest_nodev-1.0.1.dist-info/metadata.json
pytest_nodev-1.0.1.dist-info/top_level.txt
pytest_nodev-1.0.1.dist-info/zip-safe
