Metadata-Version: 2.0
Name: pytest-nodev
Version: 1.0.1
Summary: Test-driven source code search for Python.
Home-page: http://pytest-nodev.readthedocs.io
Author: Alessandro Amici
Author-email: alexamici@gmail.com
License: MIT
Download-URL: https://github.com/nodev-io/pytest-nodev/archive/1.0.1.tar.gz
Keywords: test-driven source code search plugin pytest nodev
Platform: UNKNOWN
Classifier: Development Status :: 4 - Beta
Classifier: Intended Audience :: Developers
Classifier: Topic :: Software Development :: Testing
Classifier: Framework :: Pytest
Classifier: Programming Language :: Python
Classifier: Programming Language :: Python :: 2
Classifier: Programming Language :: Python :: 2.7
Classifier: Programming Language :: Python :: 3
Classifier: Programming Language :: Python :: 3.3
Classifier: Programming Language :: Python :: 3.4
Classifier: Programming Language :: Python :: 3.5
Classifier: Programming Language :: Python :: Implementation :: CPython
Classifier: Programming Language :: Python :: Implementation :: PyPy
Classifier: Operating System :: OS Independent
Classifier: License :: OSI Approved :: MIT License
Requires-Dist: future
Requires-Dist: pytest (>=2.8.1)
Requires-Dist: pytest-timeout
